types_aiobotocore_iot1click_devices/__init__.py
types_aiobotocore_iot1click_devices/__init__.pyi
types_aiobotocore_iot1click_devices/__main__.py
types_aiobotocore_iot1click_devices/client.py
types_aiobotocore_iot1click_devices/client.pyi
types_aiobotocore_iot1click_devices/literals.py
types_aiobotocore_iot1click_devices/literals.pyi
types_aiobotocore_iot1click_devices/paginator.py
types_aiobotocore_iot1click_devices/paginator.pyi
types_aiobotocore_iot1click_devices/py.typed
types_aiobotocore_iot1click_devices/type_defs.py
types_aiobotocore_iot1click_devices/type_defs.pyi
types_aiobotocore_iot1click_devices/version.py
types_aiobotocore_iot1click_devices-2.17.0.dist-info/LICENSE
types_aiobotocore_iot1click_devices-2.17.0.dist-info/METADATA
types_aiobotocore_iot1click_devices-2.17.0.dist-info/WHEEL
types_aiobotocore_iot1click_devices-2.17.0.dist-info/top_level.txt
types_aiobotocore_iot1click_devices-2.17.0.dist-info/RECORD
